OpenLIBS/__init__.py
OpenLIBS/analysis.py
OpenLIBS/preprocessing.py
OpenLIBS/Element_Database/Ac.csv
OpenLIBS/Element_Database/Ag.csv
OpenLIBS/Element_Database/Al.csv
OpenLIBS/Element_Database/Am.csv
OpenLIBS/Element_Database/Ar.csv
OpenLIBS/Element_Database/As.csv
OpenLIBS/Element_Database/At.csv
OpenLIBS/Element_Database/Au.csv
OpenLIBS/Element_Database/B.csv
OpenLIBS/Element_Database/Ba.csv
OpenLIBS/Element_Database/Be.csv
OpenLIBS/Element_Database/Bi.csv
OpenLIBS/Element_Database/Bk.csv
OpenLIBS/Element_Database/Br.csv
OpenLIBS/Element_Database/C.csv
OpenLIBS/Element_Database/Ca.csv
OpenLIBS/Element_Database/Cd.csv
OpenLIBS/Element_Database/Ce.csv
OpenLIBS/Element_Database/Cf.csv
OpenLIBS/Element_Database/Cl.csv
OpenLIBS/Element_Database/Cm.csv
OpenLIBS/Element_Database/Co.csv
OpenLIBS/Element_Database/Cr.csv
OpenLIBS/Element_Database/Cs.csv
OpenLIBS/Element_Database/Cu.csv
OpenLIBS/Element_Database/Database_info.md
OpenLIBS/Element_Database/Dy.csv
OpenLIBS/Element_Database/Er.csv
OpenLIBS/Element_Database/Es.csv
OpenLIBS/Element_Database/Eu.csv
OpenLIBS/Element_Database/F.csv
OpenLIBS/Element_Database/Fe.csv
OpenLIBS/Element_Database/Fr.csv
OpenLIBS/Element_Database/Ga.csv
OpenLIBS/Element_Database/Gd.csv
OpenLIBS/Element_Database/Ge.csv
OpenLIBS/Element_Database/H.csv
OpenLIBS/Element_Database/He.csv
OpenLIBS/Element_Database/Hf.csv
OpenLIBS/Element_Database/Hg.csv
OpenLIBS/Element_Database/Ho.csv
OpenLIBS/Element_Database/I.csv
OpenLIBS/Element_Database/In.csv
OpenLIBS/Element_Database/Ir.csv
OpenLIBS/Element_Database/K.csv
OpenLIBS/Element_Database/Kr.csv
OpenLIBS/Element_Database/La.csv
OpenLIBS/Element_Database/Li.csv
OpenLIBS/Element_Database/Lu.csv
OpenLIBS/Element_Database/Mg.csv
OpenLIBS/Element_Database/Mn.csv
OpenLIBS/Element_Database/Mo.csv
OpenLIBS/Element_Database/N.csv
OpenLIBS/Element_Database/Na.csv
OpenLIBS/Element_Database/Nb.csv
OpenLIBS/Element_Database/Nd.csv
OpenLIBS/Element_Database/Ne.csv
OpenLIBS/Element_Database/Ni.csv
OpenLIBS-0.1.0.dist-info/LICENSE.txt
OpenLIBS-0.1.0.dist-info/METADATA
OpenLIBS-0.1.0.dist-info/WHEEL
OpenLIBS-0.1.0.dist-info/top_level.txt
OpenLIBS-0.1.0.dist-info/RECORD
