Metadata-Version: 2.1
Name: OpenLIBS
Version: 0.1.0
Summary: OpenLIBS is a package that provides functionality to analyse Laser Induced Breakdown Spectroscopic Spectras
Home-page: https://github.com/Bluejee/OpenLIBS
Author: Balakrishna Prabhu B N
Author-email: balakrishnaprabhu1999@gmail.com
License: GPL-3.0-or-later
Keywords: analysis,LIBS,spectroscopy,database,laser,Physics,Computation
Platform: UNKNOWN
Classifier: Programming Language :: Python :: 3
Classifier: Operating System :: OS Independent
Classifier: License :: OSI Approved :: GNU General Public License v3 (GPLv3)
Classifier: Intended Audience :: Education
Classifier: Intended Audience :: Developers
Classifier: Intended Audience :: Science/Research
Requires-Python: >=3.7
License-File: LICENSE.txt
Requires-Dist: pandas (>=1.4.0)
